sclmd/__init__.py
sclmd/baths.py
sclmd/brennerdriver.py
sclmd/deepmddriver.py
sclmd/functions.py
sclmd/harmonic.py
sclmd/lammpsdriver.py
sclmd/md.py
sclmd/multilmpdrivers.py
sclmd/myio.py
sclmd/negf.py
sclmd/noise.py
sclmd/selfenergy.py
sclmd/siestadriver.py
sclmd/tools.py
sclmd/units.py
sclmd-0.4.7.dist-info/LICENSE
sclmd-0.4.7.dist-info/METADATA
sclmd-0.4.7.dist-info/WHEEL
sclmd-0.4.7.dist-info/top_level.txt
sclmd-0.4.7.dist-info/zip-safe
sclmd-0.4.7.dist-info/RECORD
